txtree/WordProcessor.py
txtree/__init__.py
txtree/__main__.py
txtree/txtree.py
txtree/internal/__init__.py
txtree/internal/compute_temporal_correlation.py
txtree/internal/compute_tf_idf.py
txtree/internal/count_occurrences.py
txtree/internal/create_seqrecord_list.py
txtree/internal/estimate_scipy_linkage_mem.py
txtree/internal/estimate_scipy_linkage_n.py
txtree/internal/explode_list.py
txtree/internal/fuzzy_moving_average.py
txtree/internal/get_available_mem.py
txtree/internal/get_dendro_ord.py
txtree/internal/get_norm.py
txtree/internal/load_h5.py
txtree/internal/load_pickle.py
txtree/internal/map_docs_to_words.py
txtree/internal/map_words_to_docs.py
txtree/internal/mat_to_ete_tree.py
txtree/internal/parallelization.py
txtree/internal/pca.py
txtree/internal/rank_by_cosine_similarity.py
txtree/internal/save_h5.py
txtree/internal/save_pickle.py
txtree/internal/split_array.py
txtree/internal/tokenize.py
txtree/internal/aminocode/__init__.py
txtree/internal/aminocode/aminocode.py
txtree/internal/htmltools/HTMLSVGCreator.py
txtree/internal/htmltools/HTMLTableCreator.py
txtree/internal/htmltools/__init__.py
txtree/internal/sweep/__init__.py
txtree/internal/sweep/fasta_to_sweep.py
txtree/internal/sweep/internal/__init__.py
txtree/internal/sweep/internal/aa_to_int.py
txtree/internal/sweep/internal/aa_to_num.py
txtree/internal/sweep/internal/count_occ.py
txtree/internal/sweep/internal/lambert_w.py
txtree/internal/sweep/internal/load_matrix_from_path.py
txtree/internal/sweep/internal/scan_mask.py
txtree/internal/sweep/internal/transform_with_lambert_w.py
txtree/internal/sweep/utils/__init__.py
txtree/internal/sweep/utils/create_proj_mat.py
txtree/internal/sweep/utils/create_sweep_masks.py
txtree/internal/sweep/utils/fastaread.py
txtree/internal/sweep/utils/orthrand.py
txtree/utils/__init__.py
txtree/utils/create_html_tm.py
txtree/utils/medline_to_html_tm.py
txtree/utils/medline_to_xml.py
txtree/utils/xml_to_temporal_correlation.py
txtree/utils/xml_to_word_processor.py
txtree-2025.7.17.dist-info/licenses/LICENSE.txt
txtree-2025.7.17.dist-info/METADATA
txtree-2025.7.17.dist-info/WHEEL
txtree-2025.7.17.dist-info/top_level.txt
txtree-2025.7.17.dist-info/RECORD
